shrimpy/__init__.py
shrimpy/test.py
shrim_py-0.0.2.dist-info/LICENSE
shrim_py-0.0.2.dist-info/METADATA
shrim_py-0.0.2.dist-info/WHEEL
shrim_py-0.0.2.dist-info/top_level.txt
shrim_py-0.0.2.dist-info/RECORD
