Metadata-Version: 2.1
Name: shrim-py
Version: 0.0.2
Summary: The Better Shrimpy Python Client for Dev and User APIs
Home-page: https://github.com/Cryptogram-Trade/shrim-py
Author: Cryptogram Trade
Author-email: dev@cryptogram.trade
License: GNU
Keywords: shrimpy,social,bitcoin,client,api,exchange,crypto,currency,trading,ETH,BTC,3commas
Platform: UNKNOWN
Classifier: Programming Language :: Python :: 3
Classifier: License :: OSI Approved :: GNU Affero General Public License v3
Classifier: Operating System :: OS Independent
Requires-Python: >=3.6
Requires-Dist: requests (>=2.25.1)
